shotgun_extensions/__init__.py
shotgun_extensions/query_fields.py
tests/__init__.py
tests/unit/__init__.py
tests/unit/test_query_fields.py
tests/unit/test_version.py
shotgun_extensions-1.0.5.dist-info/LICENSE
shotgun_extensions-1.0.5.dist-info/METADATA
shotgun_extensions-1.0.5.dist-info/WHEEL
shotgun_extensions-1.0.5.dist-info/top_level.txt
shotgun_extensions-1.0.5.dist-info/RECORD
