Metadata-Version: 2.1
Name: shotgun-extensions
Version: 1.0.5
Summary: shotgun_extensions extends the functionality of shotgun_api3 Python package
Home-page: https://github.com/mbsurfer/shotgun-extensions
Author: Ryan Neldner
Author-email: rneldner@gmail.com
Classifier: Intended Audience :: Developers
Classifier: Programming Language :: Python
Classifier: Programming Language :: Python :: 3.7
Classifier: Programming Language :: Python :: 3.9
Classifier: Programming Language :: Python :: 3.10
Classifier: Programming Language :: Python :: 3.11
Classifier: Operating System :: OS Independent
Classifier: License :: OSI Approved :: MIT License
Requires-Python: >=3.7.0
License-File: LICENSE
Requires-Dist: shotgun-api3
